atlas_ftag_tools-0.2.18.dist-info/licenses/LICENSE
ftag/__init__.py
ftag/cli_utils.py
ftag/cuts.py
ftag/example_metadata.yaml
ftag/find_metadata.py
ftag/flavours.py
ftag/flavours.yaml
ftag/fraction_optimization.py
ftag/git_check.py
ftag/labeller.py
ftag/labels.py
ftag/mock.py
ftag/region.py
ftag/sample.py
ftag/track_selector.py
ftag/transform.py
ftag/vds.py
ftag/working_points.py
ftag/hdf5/__init__.py
ftag/hdf5/h5add_col.py
ftag/hdf5/h5move.py
ftag/hdf5/h5reader.py
ftag/hdf5/h5split.py
ftag/hdf5/h5utils.py
ftag/hdf5/h5writer.py
ftag/utils/__init__.py
ftag/utils/logging.py
ftag/utils/metrics.py
atlas_ftag_tools-0.2.18.dist-info/METADATA
atlas_ftag_tools-0.2.18.dist-info/WHEEL
atlas_ftag_tools-0.2.18.dist-info/entry_points.txt
atlas_ftag_tools-0.2.18.dist-info/top_level.txt
atlas_ftag_tools-0.2.18.dist-info/RECORD
