Metadata-Version: 2.4
Name: atlas-ftag-tools
Version: 0.2.18
Summary: ATLAS Flavour Tagging Tools
Author: Sam Van Stroud, Philipp Gadow, Alexander Froch
License: MIT
Project-URL: Homepage, https://github.com/umami-hep/atlas-ftag-tools/
Project-URL: Issue Tracker, https://github.com/umami-hep/atlas-ftag-tools/issues
Requires-Python: <3.12,>=3.10
License-File: LICENSE
Requires-Dist: h5py>=3.14.0
Requires-Dist: numpy>=2.2.6
Requires-Dist: PyYAML>=6.0.2
Requires-Dist: scipy>=1.15.3
Provides-Extra: dev
Requires-Dist: ipykernel>=6.30.1; extra == "dev"
Requires-Dist: mypy>=1.18.1; extra == "dev"
Requires-Dist: pre-commit>=4.3.0; extra == "dev"
Requires-Dist: pydoclint>=0.7.3; extra == "dev"
Requires-Dist: pytest_notebook>=0.10.0; extra == "dev"
Requires-Dist: pytest-cov>=7.0.0; extra == "dev"
Requires-Dist: pytest>=8.4.2; extra == "dev"
Requires-Dist: ruff>=0.13.0; extra == "dev"
Dynamic: license-file
